README.rst
setup.py
docs/HISTORY.txt
wm/__init__.py
wm.chimpimport.egg-info/PKG-INFO
wm.chimpimport.egg-info/SOURCES.txt
wm.chimpimport.egg-info/dependency_links.txt
wm.chimpimport.egg-info/entry_points.txt
wm.chimpimport.egg-info/namespace_packages.txt
wm.chimpimport.egg-info/requires.txt
wm.chimpimport.egg-info/top_level.txt
wm.chimpimport.egg-info/zip-safe
wm/chimpimport/__init__.py