Metadata-Version: 1.0
Name: wm.chimpimport
Version: 1.2
Summary: automated way to import `role addresses` into mailchimp subscription lists
Home-page: https://github.com/frisi/wm.chimpimport
Author: Harald Friessnegger
Author-email: harald at webmeisterei (dot) com
License: GPL
Keywords: mailchimp import
Platform: UNKNOWN
Classifier: Programming Language :: Python
